kafka_connect_healthcheck/__init__.py
kafka_connect_healthcheck/handler.py
kafka_connect_healthcheck/health.py
kafka_connect_healthcheck/helpers.py
kafka_connect_healthcheck/main.py
kafka_connect_healthcheck/parser.py
kafka_connect_healthcheck/version.py
kafka_connect_healthcheck-0.3.0.dist-info/LICENSE
kafka_connect_healthcheck-0.3.0.dist-info/METADATA
kafka_connect_healthcheck-0.3.0.dist-info/WHEEL
kafka_connect_healthcheck-0.3.0.dist-info/entry_points.txt
kafka_connect_healthcheck-0.3.0.dist-info/top_level.txt
kafka_connect_healthcheck-0.3.0.dist-info/RECORD
