Metadata-Version: 2.1
Name: kafka-connect-healthcheck
Version: 0.3.0
Summary: A simple healthcheck wrapper to monitor Kafka Connect.
Home-page: https://github.com/devshawn/kafka-connect-healthcheck
Author: Shawn Seymour
Author-email: shawn@devshawn.com
License: Apache License 2.0
Keywords: kafka,connect,health,healthcheck,wrapper,monitor,connector
Platform: UNKNOWN
Classifier: Development Status :: 4 - Beta
Classifier: Intended Audience :: Developers
Classifier: Intended Audience :: System Administrators
Classifier: License :: OSI Approved :: Apache Software License
Classifier: Natural Language :: English
Classifier: Operating System :: MacOS
Classifier: Operating System :: Unix
Classifier: Programming Language :: Python :: 3
Classifier: Programming Language :: Python :: 3.5
Classifier: Programming Language :: Python :: 3.6
Classifier: Programming Language :: Python :: 3.7
Classifier: Programming Language :: Python :: 3.8
Classifier: Topic :: Software Development
Classifier: Topic :: Software Development :: Libraries :: Python Modules
Requires-Dist: requests (>=2.21.0)
